odoo/addons/document_knowledge/README.rst
odoo/addons/document_knowledge/__init__.py
odoo/addons/document_knowledge/__manifest__.py
odoo/addons/document_knowledge/data/ir_module_category.xml
odoo/addons/document_knowledge/data/res_users.xml
odoo/addons/document_knowledge/demo/document_knowledge.xml
odoo/addons/document_knowledge/i18n/am.po
odoo/addons/document_knowledge/i18n/ar.po
odoo/addons/document_knowledge/i18n/bg.po
odoo/addons/document_knowledge/i18n/bs.po
odoo/addons/document_knowledge/i18n/ca.po
odoo/addons/document_knowledge/i18n/cs.po
odoo/addons/document_knowledge/i18n/da.po
odoo/addons/document_knowledge/i18n/de.po
odoo/addons/document_knowledge/i18n/document_knowledge.pot
odoo/addons/document_knowledge/i18n/el.po
odoo/addons/document_knowledge/i18n/el_GR.po
odoo/addons/document_knowledge/i18n/en_AU.po
odoo/addons/document_knowledge/i18n/en_GB.po
odoo/addons/document_knowledge/i18n/es.po
odoo/addons/document_knowledge/i18n/es_AR.po
odoo/addons/document_knowledge/i18n/es_CL.po
odoo/addons/document_knowledge/i18n/es_CO.po
odoo/addons/document_knowledge/i18n/es_CR.po
odoo/addons/document_knowledge/i18n/es_DO.po
odoo/addons/document_knowledge/i18n/es_EC.po
odoo/addons/document_knowledge/i18n/es_ES.po
odoo/addons/document_knowledge/i18n/es_MX.po
odoo/addons/document_knowledge/i18n/es_PY.po
odoo/addons/document_knowledge/i18n/es_VE.po
odoo/addons/document_knowledge/i18n/et.po
odoo/addons/document_knowledge/i18n/eu.po
odoo/addons/document_knowledge/i18n/fa.po
odoo/addons/document_knowledge/i18n/fi.po
odoo/addons/document_knowledge/i18n/fr.po
odoo/addons/document_knowledge/i18n/fr_CA.po
odoo/addons/document_knowledge/i18n/gl.po
odoo/addons/document_knowledge/i18n/gu.po
odoo/addons/document_knowledge/i18n/he.po
odoo/addons/document_knowledge/i18n/he_IL.po
odoo/addons/document_knowledge/i18n/hi.po
odoo/addons/document_knowledge/i18n/hr.po
odoo/addons/document_knowledge/i18n/hu.po
odoo/addons/document_knowledge/i18n/hy.po
odoo/addons/document_knowledge/i18n/id.po
odoo_addon_document_knowledge-18.0.1.0.2.dist-info/METADATA
odoo_addon_document_knowledge-18.0.1.0.2.dist-info/WHEEL
odoo_addon_document_knowledge-18.0.1.0.2.dist-info/top_level.txt
odoo_addon_document_knowledge-18.0.1.0.2.dist-info/RECORD
