Metadata-Version: 2.1
Name: odoo-addon-document_knowledge
Version: 18.0.1.0.2
Requires-Python: >=3.10
Requires-Dist: odoo==18.0.*
Summary: Documents Knowledge
Home-page: https://github.com/OCA/knowledge
License: AGPL-3
Author: OpenERP SA,MONK Software, Tecnativa, ForgeFlow, Odoo Community Association (OCA)
Author-email: support@odoo-community.org
Classifier: Programming Language :: Python
Classifier: Framework :: Odoo
Classifier: Framework :: Odoo :: 18.0
Classifier: License :: OSI Approved :: GNU Affero General Public License v3
